README.rst
setup.py
libinput/__init__.py
libinput/constant.py
libinput/define.py
libinput/evcodes.py
libinput/event.py
libinput/version.py
python_libinput.egg-info/PKG-INFO
python_libinput.egg-info/SOURCES.txt
python_libinput.egg-info/dependency_links.txt
python_libinput.egg-info/requires.txt
python_libinput.egg-info/top_level.txt