Metadata-Version: 1.1
Name: python-libinput
Version: 0.1.0
Summary: Object-oriented wrapper for libinput using ctypes
Home-page: https://github.com/OzymandiasTheGreat/python-libinput
Author: Tomas Ravinskas
Author-email: tomas.rav@gmail.com
License: MIT
Platform: UNKNOWN
Classifier: Development Status :: 5 - Production/Stable
Classifier: Intended Audience :: Developers
Classifier: License :: OSI Approved :: MIT License
Classifier: Operating System :: POSIX :: Linux
Classifier: Programming Language :: Python :: 2.7
Classifier: Programming Language :: Python :: 3
Classifier: Topic :: Software Development :: Libraries
